ballparker/__init__.py
ballparker/dsl.py
ballparker/phab.py
ballparker/types.py
ballparker/visitors.py
ballparker/tests/__init__.py
ballparker/tests/data.py
ballparker/tests/test_dsl.py
ballparker/tests/test_markdown.py
ballparker-1.0.1.dist-info/COPYING.md
ballparker-1.0.1.dist-info/METADATA
ballparker-1.0.1.dist-info/WHEEL
ballparker-1.0.1.dist-info/top_level.txt
ballparker-1.0.1.dist-info/RECORD
