Metadata-Version: 2.1
Name: ballparker
Version: 1.0.1
Summary: A tool for structuring and creating ballpark estimates
Home-page: https://gitlab.com/ryanpavlik/ballparker
Author: Ryan A. Pavlik
Author-email: ryan.pavlik@collabora.com
License: Apache-2.0 AND CC0-1.0
Project-URL: Source Code and Issue Tracker, https://gitlab.com/ryanpavlik/ballparker
Project-URL: Documentation, https://ballparker.readthedocs.io
Platform: UNKNOWN
Classifier: Development Status :: 5 - Production/Stable
Classifier: Intended Audience :: Developers
Classifier: Programming Language :: Python :: 3
Classifier: Programming Language :: Python :: 3.6
Classifier: Programming Language :: Python :: 3.7
Classifier: Programming Language :: Python :: 3.8
Classifier: License :: OSI Approved :: Apache Software License
Classifier: Operating System :: OS Independent
Requires-Python: >=3.6
Requires-Dist: attrs
Requires-Dist: typing
